deep_phonemizer/__init__.py
deep_phonemizer/phonemizer.py
deep_phonemizer/preprocess.py
deep_phonemizer/result.py
deep_phonemizer/train.py
deep_phonemizer/configs/__init__.py
deep_phonemizer/model/__init__.py
deep_phonemizer/model/model.py
deep_phonemizer/model/predictor.py
deep_phonemizer/model/utils.py
deep_phonemizer/preprocessing/__init__.py
deep_phonemizer/preprocessing/text.py
deep_phonemizer/preprocessing/utils.py
deep_phonemizer/training/__init__.py
deep_phonemizer/training/dataset.py
deep_phonemizer/training/decorators.py
deep_phonemizer/training/evaluation.py
deep_phonemizer/training/losses.py
deep_phonemizer/training/metrics.py
deep_phonemizer/training/trainer.py
deep_phonemizer/utils/__init__.py
deep_phonemizer/utils/io.py
deep_phonemizer/utils/logging.py
ilt_deep_phonemizer-0.0.23.dist-info/licenses/LICENSE
mkdocs/autogen.py
ilt_deep_phonemizer-0.0.23.dist-info/METADATA
ilt_deep_phonemizer-0.0.23.dist-info/WHEEL
ilt_deep_phonemizer-0.0.23.dist-info/top_level.txt
ilt_deep_phonemizer-0.0.23.dist-info/RECORD
