Metadata-Version: 2.4
Name: ilt-deep-phonemizer
Version: 0.0.23
Summary: NRC Indigenous Language Technology Project fork of the DeepPhonemizer grapheme to phoneme conversion with deep learning library.
Author-email: Christian Schäfer <c.schaefer.home@gmail.com>, Aidan Pine <hello@aidanpine.ca>
License: MIT
Classifier: Development Status :: 4 - Beta
Classifier: Intended Audience :: Developers
Classifier: Intended Audience :: Education
Classifier: Intended Audience :: Science/Research
Classifier: License :: OSI Approved :: MIT License
Classifier: Operating System :: POSIX :: Linux
Classifier: Operating System :: MacOS :: MacOS X
Classifier: Operating System :: Microsoft :: Windows
Classifier: Programming Language :: Python :: 3
Classifier: Programming Language :: Python :: 3.6
Classifier: Programming Language :: Python :: 3.7
Classifier: Programming Language :: Python :: 3.8
Classifier: Programming Language :: Python :: 3.9
Classifier: Topic :: Scientific/Engineering
Classifier: Topic :: Software Development :: Libraries
Classifier: Topic :: Software Development :: Libraries :: Python Modules
Requires-Python: >=3.6
License-File: LICENSE
Requires-Dist: torch>=2.6.0
Requires-Dist: tqdm>=4.38.0
Requires-Dist: PyYAML>=5.1
Requires-Dist: tensorboard
Requires-Dist: certifi>=2022.12.7
Requires-Dist: wheel>=0.38.0
Requires-Dist: nltk>=3.9.1
Requires-Dist: setuptools>=65.5.1
Provides-Extra: tests
Requires-Dist: pytest-cov; extra == "tests"
Provides-Extra: docs
Requires-Dist: mkdocs; extra == "docs"
Requires-Dist: mkdocs-material; extra == "docs"
Provides-Extra: dev
Requires-Dist: bumpversion; extra == "dev"
Dynamic: license-file
